notebookManagerPackage/__init__.py
notebookManagerPackage/notebook_manager.py
notebookManagerPackage2-0.2.dist-info/METADATA
notebookManagerPackage2-0.2.dist-info/WHEEL
notebookManagerPackage2-0.2.dist-info/top_level.txt
notebookManagerPackage2-0.2.dist-info/RECORD
