Metadata-Version: 2.1
Name: notebookManagerPackage2
Version: 0.2
Summary: A package to manage the execution of multiple notebooks
Author: Shashank
Author-email: shashank.b@hoonartek.com
Classifier: Programming Language :: Python :: 3
Classifier: Operating System :: OS Independent
Requires-Python: >=3.6
